discord_self_api-1.0.0.dist-info/licenses/LICENSE
discord_selfbot/__init__.py
discord_selfbot/client.py
discord_selfbot/gateway.py
discord_selfbot/http.py
discord_selfbot/models.py
discord_selfbot/utils.py
discord_self_api-1.0.0.dist-info/METADATA
discord_self_api-1.0.0.dist-info/WHEEL
discord_self_api-1.0.0.dist-info/top_level.txt
discord_self_api-1.0.0.dist-info/RECORD
