Metadata-Version: 2.4
Name: discord-self-api
Version: 1.0.0
Summary: Discord user account API wrapper - Cross-platform support including Termux
Author: Zombie
Author-email: Zombie <darshdubey08@gmail.com>
License: MIT License
Project-URL: Homepage, https://github.com/yourusername/discord-selfbot-api
Project-URL: Documentation, https://github.com/yourusername/discord-selfbot-api#readme
Project-URL: Issues, https://github.com/yourusername/discord-selfbot-api/issues
Classifier: License :: OSI Approved :: MIT License
Classifier: Programming Language :: Python :: 3
Classifier: Operating System :: OS Independent
Classifier: Operating System :: Android
Classifier: Operating System :: POSIX :: Linux
Classifier: Operating System :: Microsoft :: Windows
Classifier: Operating System :: MacOS
Classifier: Development Status :: 4 - Beta
Classifier: Intended Audience :: Developers
Classifier: Topic :: Communications :: Chat
Requires-Python: >=3.7
License-File: LICENSE
Requires-Dist: aiohttp>=3.8.0
Requires-Dist: websockets>=10.0
Dynamic: author
Dynamic: license-file
Dynamic: requires-python
